pepomap/__init__.py
pepomap/ons.py
pepomap/storm.py
pepomap/tools.py
pepomap-0.1.0.dist-info/LICENSE
pepomap-0.1.0.dist-info/WHEEL
pepomap-0.1.0.dist-info/METADATA
pepomap-0.1.0.dist-info/RECORD
