Metadata-Version: 2.1
Name: pepomap
Version: 0.1.0
Summary: 
Home-page: https://github.com/ericmiguel/pepomap
License: MIT
Keywords: colormaps,matplotlib
Author: ericmiguel
Author-email: ericmiguel@id.uff.br
Requires-Python: >=3.8.0,<3.11
Classifier: License :: OSI Approved :: MIT License
Classifier: Programming Language :: Python :: 3
Classifier: Programming Language :: Python :: 3.10
Classifier: Programming Language :: Python :: 3.8
Classifier: Programming Language :: Python :: 3.9
Requires-Dist: matplotlib (>=3.5.0,<4.0.0)
Requires-Dist: numpy (>=1.21.4,<2.0.0)
Project-URL: Repository, https://github.com/ericmiguel/pepomap
